Metadata-Version: 1.0
Name: arcticfox
Version: 0.1
Summary: Python package for communication with the ArcticFox firmware
Home-page: https://github.com/Epictek/arcticfox-python
Author: Kieran Coldron
Author-email: kieran@coldron.com
License: GPL2
Platform: UNKNOWN
